setup.cfg
setup.py
global_lru_cache/__init__.py
global_lru_cache/global_lru_cache.py
global_lru_cache.egg-info/PKG-INFO
global_lru_cache.egg-info/SOURCES.txt
global_lru_cache.egg-info/dependency_links.txt
global_lru_cache.egg-info/requires.txt
global_lru_cache.egg-info/top_level.txt