Metadata-Version: 1.0
Name: global-lru-cache
Version: 1.0
Summary: Global LRU cache decorator
Home-page: https://github.com/guykisel/global_lru_cache
Author: Guy Kisel
Author-email: guy.kisel@gmail.com
License: ####################################################################################################
